{
  "key": 31,
  "value": "BMW",
  "addon": [
    {
      "key": 2024,
      "value": "2024",
      "addon": [
        {
          "key": 29772,
          "value": "228i Gran Coupe",
          "addon": [
            "4 Dr Sedan"
          ]
        },
        {
          "key": 28291,
          "value": "228i xDrive Gran Coupe",
          "addon": [
            "4 Dr Sedan"
          ]
        },
        {
          "key": 25811,
          "value": "230i",
          "addon": [
            "2 Dr Coupe"
          ]
        },
        {
          "key": 25812,
          "value": "230i xDrive",
          "addon": [
            "2 Dr Coupe"
          ]
        },
        {
          "key": 25756,
          "value": "330e",
          "addon": [
            "4 Dr Sedan"
          ]
        },
        {
          "key": 28506,
          "value": "330e xDrive",
          "addon": [
            "4 Dr Sedan"
          ]
        },
        {
          "key": 181,
          "value": "330i",
          "addon": [
            "4 Dr Sedan"
          ]
        },
        {
          "key": 25813,
          "value": "330i xDrive",
          "addon": [
            "4 Dr Sedan"
          ]
        },
        {
          "key": 1096,
          "value": "430i",
          "addon": [
            "2 Dr Convertible",
            "2 Dr Coupe"
          ]
        },
        {
          "key": 25821,
          "value": "430i Gran Coupe",
          "addon": [
            "4 Dr Hatchback"
          ]
        },
        {
          "key": 25820,
          "value": "430i xDrive",
          "addon": [
            "2 Dr Convertible",
            "2 Dr Coupe"
          ]
        },
        {
          "key": 25822,
          "value": "430i xDrive Gran Coupe",
          "addon": [
            "4 Dr Hatchback"
          ]
        },
        {
          "key": 25850,
          "value": "530i xDrive",
          "addon": [
            "4 Dr Sedan"
          ]
        },
        {
          "key": 25851,
          "value": "540i xDrive",
          "addon": [
            "4 Dr Sedan"
          ]
        },
        {
          "key": 198,
          "value": "740i",
          "addon": [
            "4 Dr Sedan"
          ]
        },
        {
          "key": 32640,
          "value": "750e xDrive",
          "addon": [
            "4 Dr Sedan"
          ]
        },
        {
          "key": 30219,
          "value": "760i xDrive",
          "addon": [
            "4 Dr Sedan"
          ]
        },
        {
          "key": 27939,
          "value": "840i",
          "addon": [
            "2 Dr Convertible",
            "2 Dr Coupe"
          ]
        },
        {
          "key": 27940,
          "value": "840i Gran Coupe",
          "addon": [
            "4 Dr Sedan"
          ]
        },
        {
          "key": 27941,
          "value": "840i xDrive",
          "addon": [
            "2 Dr Convertible",
            "2 Dr Coupe"
          ]
        },
        {
          "key": 27942,
          "value": "840i xDrive Gran Coupe",
          "addon": [
            "4 Dr Sedan"
          ]
        },
        {
          "key": 29647,
          "value": "Alpina B8 Gran Coupe",
          "addon": [
            "4 Dr Sedan"
          ]
        },
        {
          "key": 28780,
          "value": "Alpina XB7",
          "addon": [
            "4 Dr Sport Utility"
          ]
        },
        {
          "key": 29648,
          "value": "i4",
          "addon": [
            "4 Dr Hatchback"
          ]
        },
        {
          "key": 30218,
          "value": "i7",
          "addon": [
            "4 Dr Sedan"
          ]
        },
        {
          "key": 29375,
          "value": "iX",
          "addon": [
            "4 Dr Sport Utility"
          ]
        },
        {
          "key": 25750,
          "value": "M2",
          "addon": [
            "2 Dr Coupe"
          ]
        },
        {
          "key": 28292,
          "value": "M235i xDrive Gran Coupe",
          "addon": [
            "4 Dr Sedan"
          ]
        },
        {
          "key": 25809,
          "value": "M240i",
          "addon": [
            "2 Dr Coupe"
          ]
        },
        {
          "key": 25810,
          "value": "M240i xDrive",
          "addon": [
            "2 Dr Coupe"
          ]
        },
        {
          "key": 210,
          "value": "M3",
          "addon": [
            "4 Dr Sedan"
          ]
        },
        {
          "key": 27569,
          "value": "M340i",
          "addon": [
            "4 Dr Sedan"
          ]
        },
        {
          "key": 27570,
          "value": "M340i xDrive",
          "addon": [
            "4 Dr Sedan"
          ]
        },
        {
          "key": 23993,
          "value": "M4",
          "addon": [
            "2 Dr Convertible",
            "2 Dr Coupe"
          ]
        },
        {
          "key": 29376,
          "value": "M440i",
          "addon": [
            "2 Dr Convertible",
            "2 Dr Coupe"
          ]
        },
        {
          "key": 29402,
          "value": "M440i Gran Coupe",
          "addon": [
            "4 Dr Hatchback"
          ]
        },
        {
          "key": 28670,
          "value": "M440i xDrive",
          "addon": [
            "2 Dr Convertible",
            "2 Dr Coupe"
          ]
        },
        {
          "key": 29401,
          "value": "M440i xDrive Gran Coupe",
          "addon": [
            "4 Dr Hatchback"
          ]
        },
        {
          "key": 27680,
          "value": "M8",
          "addon": [
            "2 Dr Convertible",
            "2 Dr Coupe"
          ]
        },
        {
          "key": 28181,
          "value": "M8 Gran Coupe",
          "addon": [
            "4 Dr Sedan"
          ]
        },
        {
          "key": 27342,
          "value": "M850i xDrive",
          "addon": [
            "2 Dr Convertible",
            "2 Dr Coupe"
          ]
        },
        {
          "key": 28282,
          "value": "M850i xDrive Gran Coupe",
          "addon": [
            "4 Dr Sedan"
          ]
        },
        {
          "key": 21520,
          "value": "X1",
          "addon": [
            "4 Dr Sport Utility"
          ]
        },
        {
          "key": 2461,
          "value": "X3",
          "addon": [
            "4 Dr Sport Utility"
          ]
        },
        {
          "key": 24008,
          "value": "X4",
          "addon": [
            "4 Dr Sport Utility"
          ]
        },
        {
          "key": 213,
          "value": "X5",
          "addon": [
            "4 Dr Sport Utility"
          ]
        },
        {
          "key": 6803,
          "value": "X6",
          "addon": [
            "4 Dr Sport Utility"
          ]
        },
        {
          "key": 27571,
          "value": "X7",
          "addon": [
            "4 Dr Sport Utility"
          ]
        },
        {
          "key": 31175,
          "value": "XM",
          "addon": [
            "4 Dr Sport Utility"
          ]
        },
        {
          "key": 215,
          "value": "Z4",
          "addon": [
            "2 Dr Convertible"
          ]
        }
      ]
    },
    {
      "key": 2023,
      "value": "2023",
      "addon": [
        {
          "key": 29772,
          "value": "228i Gran Coupe",
          "addon": [
            "4 Dr Sedan"
          ]
        },
        {
          "key": 28291,
          "value": "228i xDrive Gran Coupe",
          "addon": [
            "4 Dr Sedan"
          ]
        },
        {
          "key": 25811,
          "value": "230i",
          "addon": [
            "2 Dr Coupe"
          ]
        },
        {
          "key": 25812,
          "value": "230i xDrive",
          "addon": [
            "2 Dr Coupe"
          ]
        },
        {
          "key": 25756,
          "value": "330e",
          "addon": [
            "4 Dr Sedan"
          ]
        },
        {
          "key": 28506,
          "value": "330e xDrive",
          "addon": [
            "4 Dr Sedan"
          ]
        },
        {
          "key": 181,
          "value": "330i",
          "addon": [
            "4 Dr Sedan"
          ]
        },
        {
          "key": 25813,
          "value": "330i xDrive",
          "addon": [
            "4 Dr Sedan"
          ]
        },
        {
          "key": 1096,
          "value": "430i",
          "addon": [
            "2 Dr Convertible",
            "2 Dr Coupe"
          ]
        },
        {
          "key": 25821,
          "value": "430i Gran Coupe",
          "addon": [
            "4 Dr Hatchback"
          ]
        },
        {
          "key": 25820,
          "value": "430i xDrive",
          "addon": [
            "2 Dr Convertible",
            "2 Dr Coupe"
          ]
        },
        {
          "key": 25822,
          "value": "430i xDrive Gran Coupe",
          "addon": [
            "4 Dr Hatchback"
          ]
        },
        {
          "key": 26834,
          "value": "530e",
          "addon": [
            "4 Dr Sedan"
          ]
        },
        {
          "key": 26835,
          "value": "530e xDrive",
          "addon": [
            "4 Dr Sedan"
          ]
        },
        {
          "key": 187,
          "value": "530i",
          "addon": [
            "4 Dr Sedan"
          ]
        },
        {
          "key": 25850,
          "value": "530i xDrive",
          "addon": [
            "4 Dr Sedan"
          ]
        },
        {
          "key": 191,
          "value": "540i",
          "addon": [
            "4 Dr Sedan"
          ]
        },
        {
          "key": 25851,
          "value": "540i xDrive",
          "addon": [
            "4 Dr Sedan"
          ]
        },
        {
          "key": 198,
          "value": "740i",
          "addon": [
            "4 Dr Sedan"
          ]
        },
        {
          "key": 30219,
          "value": "760i xDrive",
          "addon": [
            "4 Dr Sedan"
          ]
        },
        {
          "key": 27939,
          "value": "840i",
          "addon": [
            "2 Dr Convertible",
            "2 Dr Coupe"
          ]
        },
        {
          "key": 27940,
          "value": "840i Gran Coupe",
          "addon": [
            "4 Dr Sedan"
          ]
        },
        {
          "key": 27941,
          "value": "840i xDrive",
          "addon": [
            "2 Dr Convertible",
            "2 Dr Coupe"
          ]
        },
        {
          "key": 27942,
          "value": "840i xDrive Gran Coupe",
          "addon": [
            "4 Dr Sedan"
          ]
        },
        {
          "key": 29647,
          "value": "Alpina B8 Gran Coupe",
          "addon": [
            "4 Dr Sedan"
          ]
        },
        {
          "key": 28780,
          "value": "Alpina XB7",
          "addon": [
            "4 Dr Sport Utility"
          ]
        },
        {
          "key": 29648,
          "value": "i4",
          "addon": [
            "4 Dr Hatchback"
          ]
        },
        {
          "key": 30218,
          "value": "i7",
          "addon": [
            "4 Dr Sedan"
          ]
        },
        {
          "key": 29375,
          "value": "iX",
          "addon": [
            "4 Dr Sport Utility"
          ]
        },
        {
          "key": 25750,
          "value": "M2",
          "addon": [
            "2 Dr Coupe"
          ]
        },
        {
          "key": 28292,
          "value": "M235i xDrive Gran Coupe",
          "addon": [
            "4 Dr Sedan"
          ]
        },
        {
          "key": 25809,
          "value": "M240i",
          "addon": [
            "2 Dr Coupe"
          ]
        },
        {
          "key": 25810,
          "value": "M240i xDrive",
          "addon": [
            "2 Dr Coupe"
          ]
        },
        {
          "key": 210,
          "value": "M3",
          "addon": [
            "4 Dr Sedan"
          ]
        },
        {
          "key": 27569,
          "value": "M340i",
          "addon": [
            "4 Dr Sedan"
          ]
        },
        {
          "key": 27570,
          "value": "M340i xDrive",
          "addon": [
            "4 Dr Sedan"
          ]
        },
        {
          "key": 23993,
          "value": "M4",
          "addon": [
            "2 Dr Convertible",
            "2 Dr Coupe"
          ]
        },
        {
          "key": 29376,
          "value": "M440i",
          "addon": [
            "2 Dr Convertible",
            "2 Dr Coupe"
          ]
        },
        {
          "key": 29402,
          "value": "M440i Gran Coupe",
          "addon": [
            "4 Dr Hatchback"
          ]
        },
        {
          "key": 28670,
          "value": "M440i xDrive",
          "addon": [
            "2 Dr Convertible",
            "2 Dr Coupe"
          ]
        },
        {
          "key": 29401,
          "value": "M440i xDrive Gran Coupe",
          "addon": [
            "4 Dr Hatchback"
          ]
        },
        {
          "key": 211,
          "value": "M5",
          "addon": [
            "4 Dr Sedan"
          ]
        },
        {
          "key": 26555,
          "value": "M550i xDrive",
          "addon": [
            "4 Dr Sedan"
          ]
        },
        {
          "key": 27680,
          "value": "M8",
          "addon": [
            "2 Dr Convertible",
            "2 Dr Coupe"
          ]
        },
        {
          "key": 28181,
          "value": "M8 Gran Coupe",
          "addon": [
            "4 Dr Sedan"
          ]
        },
        {
          "key": 27342,
          "value": "M850i xDrive",
          "addon": [
            "2 Dr Convertible",
            "2 Dr Coupe"
          ]
        },
        {
          "key": 28282,
          "value": "M850i xDrive Gran Coupe",
          "addon": [
            "4 Dr Sedan"
          ]
        },
        {
          "key": 21520,
          "value": "X1",
          "addon": [
            "4 Dr Sport Utility"
          ]
        },
        {
          "key": 27191,
          "value": "X2",
          "addon": [
            "4 Dr Sport Utility"
          ]
        },
        {
          "key": 2461,
          "value": "X3",
          "addon": [
            "4 Dr Sport Utility"
          ]
        },
        {
          "key": 24008,
          "value": "X4",
          "addon": [
            "4 Dr Sport Utility"
          ]
        },
        {
          "key": 213,
          "value": "X5",
          "addon": [
            "4 Dr Sport Utility"
          ]
        },
        {
          "key": 6803,
          "value": "X6",
          "addon": [
            "4 Dr Sport Utility"
          ]
        },
        {
          "key": 27571,
          "value": "X7",
          "addon": [
            "4 Dr Sport Utility"
          ]
        },
        {
          "key": 31175,
          "value": "XM",
          "addon": [
            "4 Dr Sport Utility"
          ]
        },
        {
          "key": 215,
          "value": "Z4",
          "addon": [
            "2 Dr Convertible"
          ]
        }
      ]
    },
    {
      "key": 2022,
      "value": "2022",
      "addon": [
        {
          "key": 29772,
          "value": "228i Gran Coupe",
          "addon": [
            "4 Dr Sedan"
          ]
        },
        {
          "key": 28291,
          "value": "228i xDrive Gran Coupe",
          "addon": [
            "4 Dr Sedan"
          ]
        },
        {
          "key": 25811,
          "value": "230i",
          "addon": [
            "2 Dr Coupe"
          ]
        },
        {
          "key": 25756,
          "value": "330e",
          "addon": [
            "4 Dr Sedan"
          ]
        },
        {
          "key": 28506,
          "value": "330e xDrive",
          "addon": [
            "4 Dr Sedan"
          ]
        },
        {
          "key": 181,
          "value": "330i",
          "addon": [
            "4 Dr Sedan"
          ]
        },
        {
          "key": 25813,
          "value": "330i xDrive",
          "addon": [
            "4 Dr Sedan"
          ]
        },
        {
          "key": 1096,
          "value": "430i",
          "addon": [
            "2 Dr Convertible",
            "2 Dr Coupe"
          ]
        },
        {
          "key": 25821,
          "value": "430i Gran Coupe",
          "addon": [
            "4 Dr Hatchback"
          ]
        },
        {
          "key": 25820,
          "value": "430i xDrive",
          "addon": [
            "2 Dr Convertible",
            "2 Dr Coupe"
          ]
        },
        {
          "key": 26834,
          "value": "530e",
          "addon": [
            "4 Dr Sedan"
          ]
        },
        {
          "key": 26835,
          "value": "530e xDrive",
          "addon": [
            "4 Dr Sedan"
          ]
        },
        {
          "key": 187,
          "value": "530i",
          "addon": [
            "4 Dr Sedan"
          ]
        },
        {
          "key": 25850,
          "value": "530i xDrive",
          "addon": [
            "4 Dr Sedan"
          ]
        },
        {
          "key": 191,
          "value": "540i",
          "addon": [
            "4 Dr Sedan"
          ]
        },
        {
          "key": 25851,
          "value": "540i xDrive",
          "addon": [
            "4 Dr Sedan"
          ]
        },
        {
          "key": 198,
          "value": "740i",
          "addon": [
            "4 Dr Sedan"
          ]
        },
        {
          "key": 25766,
          "value": "740i xDrive",
          "addon": [
            "4 Dr Sedan"
          ]
        },
        {
          "key": 27640,
          "value": "745e xDrive",
          "addon": [
            "4 Dr Sedan"
          ]
        },
        {
          "key": 28302,
          "value": "745Le xDrive",
          "addon": [
            "4 Dr Sedan"
          ]
        },
        {
          "key": 16132,
          "value": "750i xDrive",
          "addon": [
            "4 Dr Sedan"
          ]
        },
        {
          "key": 16133,
          "value": "750Li xDrive",
          "addon": [
            "4 Dr Sedan"
          ]
        },
        {
          "key": 27939,
          "value": "840i",
          "addon": [
            "2 Dr Convertible",
            "2 Dr Coupe"
          ]
        },
        {
          "key": 27940,
          "value": "840i Gran Coupe",
          "addon": [
            "4 Dr Sedan"
          ]
        },
        {
          "key": 27941,
          "value": "840i xDrive",
          "addon": [
            "2 Dr Convertible",
            "2 Dr Coupe"
          ]
        },
        {
          "key": 27942,
          "value": "840i xDrive Gran Coupe",
          "addon": [
            "4 Dr Sedan"
          ]
        },
        {
          "key": 6330,
          "value": "Alpina B7",
          "addon": [
            "4 Dr Sedan"
          ]
        },
        {
          "key": 29647,
          "value": "Alpina B8 Gran Coupe",
          "addon": [
            "4 Dr Sedan"
          ]
        },
        {
          "key": 28780,
          "value": "Alpina XB7",
          "addon": [
            "4 Dr Sport Utility"
          ]
        },
        {
          "key": 29648,
          "value": "i4",
          "addon": [
            "4 Dr Hatchback"
          ]
        },
        {
          "key": 29375,
          "value": "iX",
          "addon": [
            "4 Dr Sport Utility"
          ]
        },
        {
          "key": 28292,
          "value": "M235i xDrive Gran Coupe",
          "addon": [
            "4 Dr Sedan"
          ]
        },
        {
          "key": 25810,
          "value": "M240i xDrive",
          "addon": [
            "2 Dr Coupe"
          ]
        },
        {
          "key": 210,
          "value": "M3",
          "addon": [
            "4 Dr Sedan"
          ]
        },
        {
          "key": 27569,
          "value": "M340i",
          "addon": [
            "4 Dr Sedan"
          ]
        },
        {
          "key": 27570,
          "value": "M340i xDrive",
          "addon": [
            "4 Dr Sedan"
          ]
        },
        {
          "key": 23993,
          "value": "M4",
          "addon": [
            "2 Dr Convertible",
            "2 Dr Coupe"
          ]
        },
        {
          "key": 29376,
          "value": "M440i",
          "addon": [
            "2 Dr Convertible",
            "2 Dr Coupe"
          ]
        },
        {
          "key": 29402,
          "value": "M440i Gran Coupe",
          "addon": [
            "4 Dr Hatchback"
          ]
        },
        {
          "key": 28670,
          "value": "M440i xDrive",
          "addon": [
            "2 Dr Convertible",
            "2 Dr Coupe"
          ]
        },
        {
          "key": 29401,
          "value": "M440i xDrive Gran Coupe",
          "addon": [
            "4 Dr Hatchback"
          ]
        },
        {
          "key": 211,
          "value": "M5",
          "addon": [
            "4 Dr Sedan"
          ]
        },
        {
          "key": 26555,
          "value": "M550i xDrive",
          "addon": [
            "4 Dr Sedan"
          ]
        },
        {
          "key": 26419,
          "value": "M760i xDrive",
          "addon": [
            "4 Dr Sedan"
          ]
        },
        {
          "key": 26836,
          "value": "M760Li xDrive",
          "addon": [
            "4 Dr Sedan"
          ]
        },
        {
          "key": 27680,
          "value": "M8",
          "addon": [
            "2 Dr Convertible",
            "2 Dr Coupe"
          ]
        },
        {
          "key": 28181,
          "value": "M8 Gran Coupe",
          "addon": [
            "4 Dr Sedan"
          ]
        },
        {
          "key": 27342,
          "value": "M850i xDrive",
          "addon": [
            "2 Dr Convertible",
            "2 Dr Coupe"
          ]
        },
        {
          "key": 28282,
          "value": "M850i xDrive Gran Coupe",
          "addon": [
            "4 Dr Sedan"
          ]
        },
        {
          "key": 21520,
          "value": "X1",
          "addon": [
            "4 Dr Sport Utility"
          ]
        },
        {
          "key": 27191,
          "value": "X2",
          "addon": [
            "4 Dr Sport Utility"
          ]
        },
        {
          "key": 2461,
          "value": "X3",
          "addon": [
            "4 Dr Sport Utility"
          ]
        },
        {
          "key": 24008,
          "value": "X4",
          "addon": [
            "4 Dr Sport Utility"
          ]
        },
        {
          "key": 213,
          "value": "X5",
          "addon": [
            "4 Dr Sport Utility"
          ]
        },
        {
          "key": 6803,
          "value": "X6",
          "addon": [
            "4 Dr Sport Utility"
          ]
        },
        {
          "key": 27571,
          "value": "X7",
          "addon": [
            "4 Dr Sport Utility"
          ]
        },
        {
          "key": 215,
          "value": "Z4",
          "addon": [
            "2 Dr Convertible"
          ]
        }
      ]
    },
    {
      "key": 2021,
      "value": "2021",
      "addon": [
        {
          "key": 29772,
          "value": "228i Gran Coupe",
          "addon": [
            "4 Dr Sedan"
          ]
        },
        {
          "key": 28291,
          "value": "228i xDrive Gran Coupe",
          "addon": [
            "4 Dr Sedan"
          ]
        },
        {
          "key": 25811,
          "value": "230i",
          "addon": [
            "2 Dr Convertible",
            "2 Dr Coupe"
          ]
        },
        {
          "key": 25812,
          "value": "230i xDrive",
          "addon": [
            "2 Dr Convertible",
            "2 Dr Coupe"
          ]
        },
        {
          "key": 25756,
          "value": "330e",
          "addon": [
            "4 Dr Sedan"
          ]
        },
        {
          "key": 28506,
          "value": "330e xDrive",
          "addon": [
            "4 Dr Sedan"
          ]
        },
        {
          "key": 181,
          "value": "330i",
          "addon": [
            "4 Dr Sedan"
          ]
        },
        {
          "key": 25813,
          "value": "330i xDrive",
          "addon": [
            "4 Dr Sedan"
          ]
        },
        {
          "key": 1096,
          "value": "430i",
          "addon": [
            "2 Dr Convertible",
            "2 Dr Coupe"
          ]
        },
        {
          "key": 25820,
          "value": "430i xDrive",
          "addon": [
            "2 Dr Coupe"
          ]
        },
        {
          "key": 26834,
          "value": "530e",
          "addon": [
            "4 Dr Sedan"
          ]
        },
        {
          "key": 26835,
          "value": "530e xDrive",
          "addon": [
            "4 Dr Sedan"
          ]
        },
        {
          "key": 187,
          "value": "530i",
          "addon": [
            "4 Dr Sedan"
          ]
        },
        {
          "key": 25850,
          "value": "530i xDrive",
          "addon": [
            "4 Dr Sedan"
          ]
        },
        {
          "key": 191,
          "value": "540i",
          "addon": [
            "4 Dr Sedan"
          ]
        },
        {
          "key": 25851,
          "value": "540i xDrive",
          "addon": [
            "4 Dr Sedan"
          ]
        },
        {
          "key": 198,
          "value": "740i",
          "addon": [
            "4 Dr Sedan"
          ]
        },
        {
          "key": 25766,
          "value": "740i xDrive",
          "addon": [
            "4 Dr Sedan"
          ]
        },
        {
          "key": 27640,
          "value": "745e xDrive",
          "addon": [
            "4 Dr Sedan"
          ]
        },
        {
          "key": 28302,
          "value": "745Le xDrive",
          "addon": [
            "4 Dr Sedan"
          ]
        },
        {
          "key": 16132,
          "value": "750i xDrive",
          "addon": [
            "4 Dr Sedan"
          ]
        },
        {
          "key": 16133,
          "value": "750Li xDrive",
          "addon": [
            "4 Dr Sedan"
          ]
        },
        {
          "key": 27939,
          "value": "840i",
          "addon": [
            "2 Dr Convertible",
            "2 Dr Coupe"
          ]
        },
        {
          "key": 27940,
          "value": "840i Gran Coupe",
          "addon": [
            "4 Dr Sedan"
          ]
        },
        {
          "key": 27941,
          "value": "840i xDrive",
          "addon": [
            "2 Dr Convertible",
            "2 Dr Coupe"
          ]
        },
        {
          "key": 27942,
          "value": "840i xDrive Gran Coupe",
          "addon": [
            "4 Dr Sedan"
          ]
        },
        {
          "key": 6330,
          "value": "Alpina B7",
          "addon": [
            "4 Dr Sedan"
          ]
        },
        {
          "key": 28780,
          "value": "Alpina XB7",
          "addon": [
            "4 Dr Sport Utility"
          ]
        },
        {
          "key": 23975,
          "value": "i3",
          "addon": [
            "4 Dr Hatchback"
          ]
        },
        {
          "key": 26894,
          "value": "i3s",
          "addon": [
            "4 Dr Hatchback"
          ]
        },
        {
          "key": 25750,
          "value": "M2",
          "addon": [
            "2 Dr Coupe"
          ]
        },
        {
          "key": 28292,
          "value": "M235i xDrive Gran Coupe",
          "addon": [
            "4 Dr Sedan"
          ]
        },
        {
          "key": 25809,
          "value": "M240i",
          "addon": [
            "2 Dr Convertible",
            "2 Dr Coupe"
          ]
        },
        {
          "key": 25810,
          "value": "M240i xDrive",
          "addon": [
            "2 Dr Convertible",
            "2 Dr Coupe"
          ]
        },
        {
          "key": 210,
          "value": "M3",
          "addon": [
            "4 Dr Sedan"
          ]
        },
        {
          "key": 27569,
          "value": "M340i",
          "addon": [
            "4 Dr Sedan"
          ]
        },
        {
          "key": 27570,
          "value": "M340i xDrive",
          "addon": [
            "4 Dr Sedan"
          ]
        },
        {
          "key": 23993,
          "value": "M4",
          "addon": [
            "2 Dr Coupe"
          ]
        },
        {
          "key": 29376,
          "value": "M440i",
          "addon": [
            "2 Dr Convertible"
          ]
        },
        {
          "key": 28670,
          "value": "M440i xDrive",
          "addon": [
            "2 Dr Coupe"
          ]
        },
        {
          "key": 211,
          "value": "M5",
          "addon": [
            "4 Dr Sedan"
          ]
        },
        {
          "key": 26555,
          "value": "M550i xDrive",
          "addon": [
            "4 Dr Sedan"
          ]
        },
        {
          "key": 26419,
          "value": "M760i xDrive",
          "addon": [
            "4 Dr Sedan"
          ]
        },
        {
          "key": 26836,
          "value": "M760Li xDrive",
          "addon": [
            "4 Dr Sedan"
          ]
        },
        {
          "key": 28181,
          "value": "M8 Gran Coupe",
          "addon": [
            "4 Dr Sedan"
          ]
        },
        {
          "key": 27342,
          "value": "M850i xDrive",
          "addon": [
            "2 Dr Convertible",
            "2 Dr Coupe"
          ]
        },
        {
          "key": 28282,
          "value": "M850i xDrive Gran Coupe",
          "addon": [
            "4 Dr Sedan"
          ]
        },
        {
          "key": 21520,
          "value": "X1",
          "addon": [
            "4 Dr Sport Utility"
          ]
        },
        {
          "key": 27191,
          "value": "X2",
          "addon": [
            "4 Dr Sport Utility"
          ]
        },
        {
          "key": 2461,
          "value": "X3",
          "addon": [
            "4 Dr Sport Utility"
          ]
        },
        {
          "key": 24008,
          "value": "X4",
          "addon": [
            "4 Dr Sport Utility"
          ]
        },
        {
          "key": 213,
          "value": "X5",
          "addon": [
            "4 Dr Sport Utility"
          ]
        },
        {
          "key": 6803,
          "value": "X6",
          "addon": [
            "4 Dr Sport Utility"
          ]
        },
        {
          "key": 27571,
          "value": "X7",
          "addon": [
            "4 Dr Sport Utility"
          ]
        },
        {
          "key": 215,
          "value": "Z4",
          "addon": [
            "2 Dr Convertible"
          ]
        }
      ]
    },
    {
      "key": 2020,
      "value": "2020",
      "addon": [
        {
          "key": 28291,
          "value": "228i xDrive Gran Coupe",
          "addon": [
            "4 Dr Sedan"
          ]
        },
        {
          "key": 25811,
          "value": "230i",
          "addon": [
            "2 Dr Convertible",
            "2 Dr Coupe"
          ]
        },
        {
          "key": 25812,
          "value": "230i xDrive",
          "addon": [
            "2 Dr Convertible",
            "2 Dr Coupe"
          ]
        },
        {
          "key": 181,
          "value": "330i",
          "addon": [
            "4 Dr Sedan"
          ]
        },
        {
          "key": 25813,
          "value": "330i xDrive",
          "addon": [
            "4 Dr Sedan"
          ]
        },
        {
          "key": 1096,
          "value": "430i",
          "addon": [
            "2 Dr Convertible",
            "2 Dr Coupe"
          ]
        },
        {
          "key": 25821,
          "value": "430i Gran Coupe",
          "addon": [
            "4 Dr Hatchback"
          ]
        },
        {
          "key": 25820,
          "value": "430i xDrive",
          "addon": [
            "2 Dr Convertible",
            "2 Dr Coupe"
          ]
        },
        {
          "key": 25822,
          "value": "430i xDrive Gran Coupe",
          "addon": [
            "4 Dr Hatchback"
          ]
        },
        {
          "key": 25816,
          "value": "440i",
          "addon": [
            "2 Dr Convertible",
            "2 Dr Coupe"
          ]
        },
        {
          "key": 25818,
          "value": "440i Gran Coupe",
          "addon": [
            "4 Dr Hatchback"
          ]
        },
        {
          "key": 25817,
          "value": "440i xDrive",
          "addon": [
            "2 Dr Convertible",
            "2 Dr Coupe"
          ]
        },
        {
          "key": 25819,
          "value": "440i xDrive Gran Coupe",
          "addon": [
            "4 Dr Hatchback"
          ]
        },
        {
          "key": 26834,
          "value": "530e",
          "addon": [
            "4 Dr Sedan"
          ]
        },
        {
          "key": 26835,
          "value": "530e xDrive",
          "addon": [
            "4 Dr Sedan"
          ]
        },
        {
          "key": 187,
          "value": "530i",
          "addon": [
            "4 Dr Sedan"
          ]
        },
        {
          "key": 25850,
          "value": "530i xDrive",
          "addon": [
            "4 Dr Sedan"
          ]
        },
        {
          "key": 191,
          "value": "540i",
          "addon": [
            "4 Dr Sedan"
          ]
        },
        {
          "key": 25851,
          "value": "540i xDrive",
          "addon": [
            "4 Dr Sedan"
          ]
        },
        {
          "key": 198,
          "value": "740i",
          "addon": [
            "4 Dr Sedan"
          ]
        },
        {
          "key": 25766,
          "value": "740i xDrive",
          "addon": [
            "4 Dr Sedan"
          ]
        },
        {
          "key": 27640,
          "value": "745e xDrive",
          "addon": [
            "4 Dr Sedan"
          ]
        },
        {
          "key": 28302,
          "value": "745Le xDrive",
          "addon": [
            "4 Dr Sedan"
          ]
        },
        {
          "key": 16132,
          "value": "750i xDrive",
          "addon": [
            "4 Dr Sedan"
          ]
        },
        {
          "key": 16133,
          "value": "750Li xDrive",
          "addon": [
            "4 Dr Sedan"
          ]
        },
        {
          "key": 27939,
          "value": "840i",
          "addon": [
            "2 Dr Convertible",
            "2 Dr Coupe"
          ]
        },
        {
          "key": 27940,
          "value": "840i Gran Coupe",
          "addon": [
            "4 Dr Sedan"
          ]
        },
        {
          "key": 27941,
          "value": "840i xDrive",
          "addon": [
            "2 Dr Convertible",
            "2 Dr Coupe"
          ]
        },
        {
          "key": 27942,
          "value": "840i xDrive Gran Coupe",
          "addon": [
            "4 Dr Sedan"
          ]
        },
        {
          "key": 6330,
          "value": "Alpina B7",
          "addon": [
            "4 Dr Sedan"
          ]
        },
        {
          "key": 23975,
          "value": "i3",
          "addon": [
            "4 Dr Hatchback"
          ]
        },
        {
          "key": 26894,
          "value": "i3s",
          "addon": [
            "4 Dr Hatchback"
          ]
        },
        {
          "key": 24258,
          "value": "i8",
          "addon": [
            "2 Dr Convertible",
            "2 Dr Coupe"
          ]
        },
        {
          "key": 25750,
          "value": "M2",
          "addon": [
            "2 Dr Coupe"
          ]
        },
        {
          "key": 28292,
          "value": "M235i xDrive Gran Coupe",
          "addon": [
            "4 Dr Sedan"
          ]
        },
        {
          "key": 25809,
          "value": "M240i",
          "addon": [
            "2 Dr Convertible",
            "2 Dr Coupe"
          ]
        },
        {
          "key": 25810,
          "value": "M240i xDrive",
          "addon": [
            "2 Dr Convertible",
            "2 Dr Coupe"
          ]
        },
        {
          "key": 27569,
          "value": "M340i",
          "addon": [
            "4 Dr Sedan"
          ]
        },
        {
          "key": 27570,
          "value": "M340i xDrive",
          "addon": [
            "4 Dr Sedan"
          ]
        },
        {
          "key": 23993,
          "value": "M4",
          "addon": [
            "2 Dr Convertible",
            "2 Dr Coupe"
          ]
        },
        {
          "key": 211,
          "value": "M5",
          "addon": [
            "4 Dr Sedan"
          ]
        },
        {
          "key": 26555,
          "value": "M550i xDrive",
          "addon": [
            "4 Dr Sedan"
          ]
        },
        {
          "key": 26419,
          "value": "M760i xDrive",
          "addon": [
            "4 Dr Sedan"
          ]
        },
        {
          "key": 26836,
          "value": "M760Li xDrive",
          "addon": [
            "4 Dr Sedan"
          ]
        },
        {
          "key": 27680,
          "value": "M8",
          "addon": [
            "2 Dr Convertible",
            "2 Dr Coupe"
          ]
        },
        {
          "key": 28181,
          "value": "M8 Gran Coupe",
          "addon": [
            "4 Dr Sedan"
          ]
        },
        {
          "key": 27342,
          "value": "M850i xDrive",
          "addon": [
            "2 Dr Convertible",
            "2 Dr Coupe"
          ]
        },
        {
          "key": 28282,
          "value": "M850i xDrive Gran Coupe",
          "addon": [
            "4 Dr Sedan"
          ]
        },
        {
          "key": 21520,
          "value": "X1",
          "addon": [
            "4 Dr Sport Utility"
          ]
        },
        {
          "key": 27191,
          "value": "X2",
          "addon": [
            "4 Dr Sport Utility"
          ]
        },
        {
          "key": 2461,
          "value": "X3",
          "addon": [
            "4 Dr Sport Utility"
          ]
        },
        {
          "key": 24008,
          "value": "X4",
          "addon": [
            "4 Dr Sport Utility"
          ]
        },
        {
          "key": 213,
          "value": "X5",
          "addon": [
            "4 Dr Sport Utility"
          ]
        },
        {
          "key": 6803,
          "value": "X6",
          "addon": [
            "4 Dr Sport Utility"
          ]
        },
        {
          "key": 27571,
          "value": "X7",
          "addon": [
            "4 Dr Sport Utility"
          ]
        },
        {
          "key": 215,
          "value": "Z4",
          "addon": [
            "2 Dr Convertible"
          ]
        }
      ]
    },
    {
      "key": 2019,
      "value": "2019",
      "addon": [
        {
          "key": 25811,
          "value": "230i",
          "addon": [
            "2 Dr Convertible",
            "2 Dr Coupe"
          ]
        },
        {
          "key": 25812,
          "value": "230i xDrive",
          "addon": [
            "2 Dr Convertible",
            "2 Dr Coupe"
          ]
        },
        {
          "key": 181,
          "value": "330i",
          "addon": [
            "4 Dr Sedan"
          ]
        },
        {
          "key": 25814,
          "value": "330i GT xDrive",
          "addon": [
            "4 Dr Hatchback"
          ]
        },
        {
          "key": 25813,
          "value": "330i xDrive",
          "addon": [
            "4 Dr Sedan",
            "4 Dr Wagon"
          ]
        },
        {
          "key": 25815,
          "value": "340i GT xDrive",
          "addon": [
            "4 Dr Hatchback"
          ]
        },
        {
          "key": 1096,
          "value": "430i",
          "addon": [
            "2 Dr Convertible",
            "2 Dr Coupe"
          ]
        },
        {
          "key": 25821,
          "value": "430i Gran Coupe",
          "addon": [
            "4 Dr Hatchback"
          ]
        },
        {
          "key": 25820,
          "value": "430i xDrive",
          "addon": [
            "2 Dr Convertible",
            "2 Dr Coupe"
          ]
        },
        {
          "key": 25822,
          "value": "430i xDrive Gran Coupe",
          "addon": [
            "4 Dr Hatchback"
          ]
        },
        {
          "key": 25816,
          "value": "440i",
          "addon": [
            "2 Dr Convertible",
            "2 Dr Coupe"
          ]
        },
        {
          "key": 25818,
          "value": "440i Gran Coupe",
          "addon": [
            "4 Dr Hatchback"
          ]
        },
        {
          "key": 25817,
          "value": "440i xDrive",
          "addon": [
            "2 Dr Convertible",
            "2 Dr Coupe"
          ]
        },
        {
          "key": 25819,
          "value": "440i xDrive Gran Coupe",
          "addon": [
            "4 Dr Hatchback"
          ]
        },
        {
          "key": 26834,
          "value": "530e",
          "addon": [
            "4 Dr Sedan"
          ]
        },
        {
          "key": 26835,
          "value": "530e xDrive",
          "addon": [
            "4 Dr Sedan"
          ]
        },
        {
          "key": 187,
          "value": "530i",
          "addon": [
            "4 Dr Sedan"
          ]
        },
        {
          "key": 25850,
          "value": "530i xDrive",
          "addon": [
            "4 Dr Sedan"
          ]
        },
        {
          "key": 191,
          "value": "540i",
          "addon": [
            "4 Dr Sedan"
          ]
        },
        {
          "key": 25851,
          "value": "540i xDrive",
          "addon": [
            "4 Dr Sedan"
          ]
        },
        {
          "key": 21594,
          "value": "640i Gran Coupe",
          "addon": [
            "4 Dr Sedan"
          ]
        },
        {
          "key": 23446,
          "value": "640i xDrive Gran Coupe",
          "addon": [
            "4 Dr Sedan"
          ]
        },
        {
          "key": 27205,
          "value": "640i xDrive Gran Turismo",
          "addon": [
            "4 Dr Hatchback"
          ]
        },
        {
          "key": 22634,
          "value": "650i Gran Coupe",
          "addon": [
            "4 Dr Sedan"
          ]
        },
        {
          "key": 23444,
          "value": "650i xDrive Gran Coupe",
          "addon": [
            "4 Dr Sedan"
          ]
        },
        {
          "key": 25856,
          "value": "740e xDrive",
          "addon": [
            "4 Dr Sedan"
          ]
        },
        {
          "key": 198,
          "value": "740i",
          "addon": [
            "4 Dr Sedan"
          ]
        },
        {
          "key": 25766,
          "value": "740i xDrive",
          "addon": [
            "4 Dr Sedan"
          ]
        },
        {
          "key": 2795,
          "value": "750i",
          "addon": [
            "4 Dr Sedan"
          ]
        },
        {
          "key": 16132,
          "value": "750i xDrive",
          "addon": [
            "4 Dr Sedan"
          ]
        },
        {
          "key": 16133,
          "value": "750Li xDrive",
          "addon": [
            "4 Dr Sedan"
          ]
        },
        {
          "key": 24257,
          "value": "Alpina B6 xDrive Gran Coupe",
          "addon": [
            "4 Dr Sedan"
          ]
        },
        {
          "key": 6330,
          "value": "Alpina B7",
          "addon": [
            "4 Dr Sedan"
          ]
        },
        {
          "key": 23975,
          "value": "i3",
          "addon": [
            "4 Dr Hatchback"
          ]
        },
        {
          "key": 26894,
          "value": "i3s",
          "addon": [
            "4 Dr Hatchback"
          ]
        },
        {
          "key": 24258,
          "value": "i8",
          "addon": [
            "2 Dr Convertible",
            "2 Dr Coupe"
          ]
        },
        {
          "key": 25750,
          "value": "M2",
          "addon": [
            "2 Dr Coupe"
          ]
        },
        {
          "key": 25809,
          "value": "M240i",
          "addon": [
            "2 Dr Convertible",
            "2 Dr Coupe"
          ]
        },
        {
          "key": 25810,
          "value": "M240i xDrive",
          "addon": [
            "2 Dr Convertible",
            "2 Dr Coupe"
          ]
        },
        {
          "key": 23993,
          "value": "M4",
          "addon": [
            "2 Dr Convertible",
            "2 Dr Coupe"
          ]
        },
        {
          "key": 211,
          "value": "M5",
          "addon": [
            "4 Dr Sedan"
          ]
        },
        {
          "key": 26555,
          "value": "M550i xDrive",
          "addon": [
            "4 Dr Sedan"
          ]
        },
        {
          "key": 23443,
          "value": "M6 Gran Coupe",
          "addon": [
            "4 Dr Sedan"
          ]
        },
        {
          "key": 26419,
          "value": "M760i xDrive",
          "addon": [
            "4 Dr Sedan"
          ]
        },
        {
          "key": 26836,
          "value": "M760Li xDrive",
          "addon": [
            "4 Dr Sedan"
          ]
        },
        {
          "key": 27342,
          "value": "M850i xDrive",
          "addon": [
            "2 Dr Convertible",
            "2 Dr Coupe"
          ]
        },
        {
          "key": 21520,
          "value": "X1",
          "addon": [
            "4 Dr Sport Utility"
          ]
        },
        {
          "key": 27191,
          "value": "X2",
          "addon": [
            "4 Dr Sport Utility"
          ]
        },
        {
          "key": 2461,
          "value": "X3",
          "addon": [
            "4 Dr Sport Utility"
          ]
        },
        {
          "key": 24008,
          "value": "X4",
          "addon": [
            "4 Dr Sport Utility"
          ]
        },
        {
          "key": 213,
          "value": "X5",
          "addon": [
            "4 Dr Sport Utility"
          ]
        },
        {
          "key": 6803,
          "value": "X6",
          "addon": [
            "4 Dr Sport Utility"
          ]
        },
        {
          "key": 27571,
          "value": "X7",
          "addon": [
            "4 Dr Sport Utility"
          ]
        },
        {
          "key": 215,
          "value": "Z4",
          "addon": [
            "2 Dr Convertible"
          ]
        }
      ]
    },
    {
      "key": 2018,
      "value": "2018",
      "addon": [
        {
          "key": 25811,
          "value": "230i",
          "addon": [
            "2 Dr Convertible",
            "2 Dr Coupe"
          ]
        },
        {
          "key": 25812,
          "value": "230i xDrive",
          "addon": [
            "2 Dr Convertible",
            "2 Dr Coupe"
          ]
        },
        {
          "key": 165,
          "value": "320i",
          "addon": [
            "4 Dr Sedan"
          ]
        },
        {
          "key": 22944,
          "value": "320i xDrive",
          "addon": [
            "4 Dr Sedan"
          ]
        },
        {
          "key": 23524,
          "value": "328d",
          "addon": [
            "4 Dr Sedan"
          ]
        },
        {
          "key": 23525,
          "value": "328d xDrive",
          "addon": [
            "4 Dr Sedan",
            "4 Dr Wagon"
          ]
        },
        {
          "key": 25756,
          "value": "330e",
          "addon": [
            "4 Dr Sedan"
          ]
        },
        {
          "key": 181,
          "value": "330i",
          "addon": [
            "4 Dr Sedan"
          ]
        },
        {
          "key": 25814,
          "value": "330i GT xDrive",
          "addon": [
            "4 Dr Hatchback"
          ]
        },
        {
          "key": 25813,
          "value": "330i xDrive",
          "addon": [
            "4 Dr Sedan",
            "4 Dr Wagon"
          ]
        },
        {
          "key": 25096,
          "value": "340i",
          "addon": [
            "4 Dr Sedan"
          ]
        },
        {
          "key": 25815,
          "value": "340i GT xDrive",
          "addon": [
            "4 Dr Hatchback"
          ]
        },
        {
          "key": 25097,
          "value": "340i xDrive",
          "addon": [
            "4 Dr Sedan"
          ]
        },
        {
          "key": 1096,
          "value": "430i",
          "addon": [
            "2 Dr Convertible",
            "2 Dr Coupe"
          ]
        },
        {
          "key": 25821,
          "value": "430i Gran Coupe",
          "addon": [
            "4 Dr Hatchback"
          ]
        },
        {
          "key": 25820,
          "value": "430i xDrive",
          "addon": [
            "2 Dr Convertible",
            "2 Dr Coupe"
          ]
        },
        {
          "key": 25822,
          "value": "430i xDrive Gran Coupe",
          "addon": [
            "4 Dr Hatchback"
          ]
        },
        {
          "key": 25816,
          "value": "440i",
          "addon": [
            "2 Dr Convertible",
            "2 Dr Coupe"
          ]
        },
        {
          "key": 25818,
          "value": "440i Gran Coupe",
          "addon": [
            "4 Dr Hatchback"
          ]
        },
        {
          "key": 25817,
          "value": "440i xDrive",
          "addon": [
            "2 Dr Convertible",
            "2 Dr Coupe"
          ]
        },
        {
          "key": 25819,
          "value": "440i xDrive Gran Coupe",
          "addon": [
            "4 Dr Hatchback"
          ]
        },
        {
          "key": 26834,
          "value": "530e",
          "addon": [
            "4 Dr Sedan"
          ]
        },
        {
          "key": 26835,
          "value": "530e xDrive",
          "addon": [
            "4 Dr Sedan"
          ]
        },
        {
          "key": 187,
          "value": "530i",
          "addon": [
            "4 Dr Sedan"
          ]
        },
        {
          "key": 25850,
          "value": "530i xDrive",
          "addon": [
            "4 Dr Sedan"
          ]
        },
        {
          "key": 27432,
          "value": "540d xDrive",
          "addon": [
            "4 Dr Sedan"
          ]
        },
        {
          "key": 191,
          "value": "540i",
          "addon": [
            "4 Dr Sedan"
          ]
        },
        {
          "key": 25851,
          "value": "540i xDrive",
          "addon": [
            "4 Dr Sedan"
          ]
        },
        {
          "key": 21518,
          "value": "640i",
          "addon": [
            "2 Dr Convertible",
            "2 Dr Coupe"
          ]
        },
        {
          "key": 21594,
          "value": "640i Gran Coupe",
          "addon": [
            "4 Dr Sedan"
          ]
        },
        {
          "key": 23445,
          "value": "640i xDrive",
          "addon": [
            "2 Dr Convertible",
            "2 Dr Coupe"
          ]
        },
        {
          "key": 23446,
          "value": "640i xDrive Gran Coupe",
          "addon": [
            "4 Dr Sedan"
          ]
        },
        {
          "key": 27205,
          "value": "640i xDrive Gran Turismo",
          "addon": [
            "4 Dr Hatchback"
          ]
        },
        {
          "key": 2827,
          "value": "650i",
          "addon": [
            "2 Dr Convertible",
            "2 Dr Coupe"
          ]
        },
        {
          "key": 22634,
          "value": "650i Gran Coupe",
          "addon": [
            "4 Dr Sedan"
          ]
        },
        {
          "key": 21519,
          "value": "650i xDrive",
          "addon": [
            "2 Dr Convertible",
            "2 Dr Coupe"
          ]
        },
        {
          "key": 23444,
          "value": "650i xDrive Gran Coupe",
          "addon": [
            "4 Dr Sedan"
          ]
        },
        {
          "key": 25856,
          "value": "740e xDrive",
          "addon": [
            "4 Dr Sedan"
          ]
        },
        {
          "key": 198,
          "value": "740i",
          "addon": [
            "4 Dr Sedan"
          ]
        },
        {
          "key": 25766,
          "value": "740i xDrive",
          "addon": [
            "4 Dr Sedan"
          ]
        },
        {
          "key": 2795,
          "value": "750i",
          "addon": [
            "4 Dr Sedan"
          ]
        },
        {
          "key": 16132,
          "value": "750i xDrive",
          "addon": [
            "4 Dr Sedan"
          ]
        },
        {
          "key": 16133,
          "value": "750Li xDrive",
          "addon": [
            "4 Dr Sedan"
          ]
        },
        {
          "key": 24257,
          "value": "Alpina B6 xDrive Gran Coupe",
          "addon": [
            "4 Dr Sedan"
          ]
        },
        {
          "key": 6330,
          "value": "Alpina B7",
          "addon": [
            "4 Dr Sedan"
          ]
        },
        {
          "key": 23975,
          "value": "i3",
          "addon": [
            "4 Dr Hatchback"
          ]
        },
        {
          "key": 26894,
          "value": "i3s",
          "addon": [
            "4 Dr Hatchback"
          ]
        },
        {
          "key": 25750,
          "value": "M2",
          "addon": [
            "2 Dr Coupe"
          ]
        },
        {
          "key": 25809,
          "value": "M240i",
          "addon": [
            "2 Dr Convertible",
            "2 Dr Coupe"
          ]
        },
        {
          "key": 25810,
          "value": "M240i xDrive",
          "addon": [
            "2 Dr Convertible",
            "2 Dr Coupe"
          ]
        },
        {
          "key": 210,
          "value": "M3",
          "addon": [
            "4 Dr Sedan"
          ]
        },
        {
          "key": 23993,
          "value": "M4",
          "addon": [
            "2 Dr Convertible",
            "2 Dr Coupe"
          ]
        },
        {
          "key": 211,
          "value": "M5",
          "addon": [
            "4 Dr Sedan"
          ]
        },
        {
          "key": 26555,
          "value": "M550i xDrive",
          "addon": [
            "4 Dr Sedan"
          ]
        },
        {
          "key": 212,
          "value": "M6",
          "addon": [
            "2 Dr Convertible"
          ]
        },
        {
          "key": 23443,
          "value": "M6 Gran Coupe",
          "addon": [
            "4 Dr Sedan"
          ]
        },
        {
          "key": 26419,
          "value": "M760i xDrive",
          "addon": [
            "4 Dr Sedan"
          ]
        },
        {
          "key": 26836,
          "value": "M760Li xDrive",
          "addon": [
            "4 Dr Sedan"
          ]
        },
        {
          "key": 21520,
          "value": "X1",
          "addon": [
            "4 Dr Sport Utility"
          ]
        },
        {
          "key": 27191,
          "value": "X2",
          "addon": [
            "4 Dr Sport Utility"
          ]
        },
        {
          "key": 2461,
          "value": "X3",
          "addon": [
            "4 Dr Sport Utility"
          ]
        },
        {
          "key": 24008,
          "value": "X4",
          "addon": [
            "4 Dr Sport Utility"
          ]
        },
        {
          "key": 213,
          "value": "X5",
          "addon": [
            "4 Dr Sport Utility"
          ]
        },
        {
          "key": 6803,
          "value": "X6",
          "addon": [
            "4 Dr Sport Utility"
          ]
        }
      ]
    },
    {
      "key": 2017,
      "value": "2017",
      "addon": [
        {
          "key": 25811,
          "value": "230i",
          "addon": [
            "2 Dr Convertible",
            "2 Dr Coupe"
          ]
        },
        {
          "key": 25812,
          "value": "230i xDrive",
          "addon": [
            "2 Dr Convertible",
            "2 Dr Coupe"
          ]
        },
        {
          "key": 165,
          "value": "320i",
          "addon": [
            "4 Dr Sedan"
          ]
        },
        {
          "key": 22944,
          "value": "320i xDrive",
          "addon": [
            "4 Dr Sedan"
          ]
        },
        {
          "key": 23524,
          "value": "328d",
          "addon": [
            "4 Dr Sedan"
          ]
        },
        {
          "key": 23525,
          "value": "328d xDrive",
          "addon": [
            "4 Dr Sedan",
            "4 Dr Wagon"
          ]
        },
        {
          "key": 25756,
          "value": "330e",
          "addon": [
            "4 Dr Sedan"
          ]
        },
        {
          "key": 181,
          "value": "330i",
          "addon": [
            "4 Dr Sedan"
          ]
        },
        {
          "key": 25814,
          "value": "330i GT xDrive",
          "addon": [
            "4 Dr Hatchback"
          ]
        },
        {
          "key": 25813,
          "value": "330i xDrive",
          "addon": [
            "4 Dr Sedan",
            "4 Dr Wagon"
          ]
        },
        {
          "key": 25096,
          "value": "340i",
          "addon": [
            "4 Dr Sedan"
          ]
        },
        {
          "key": 25815,
          "value": "340i GT xDrive",
          "addon": [
            "4 Dr Hatchback"
          ]
        },
        {
          "key": 25097,
          "value": "340i xDrive",
          "addon": [
            "4 Dr Sedan"
          ]
        },
        {
          "key": 1096,
          "value": "430i",
          "addon": [
            "2 Dr Convertible",
            "2 Dr Coupe"
          ]
        },
        {
          "key": 25821,
          "value": "430i Gran Coupe",
          "addon": [
            "4 Dr Hatchback"
          ]
        },
        {
          "key": 25820,
          "value": "430i xDrive",
          "addon": [
            "2 Dr Convertible",
            "2 Dr Coupe"
          ]
        },
        {
          "key": 25822,
          "value": "430i xDrive Gran Coupe",
          "addon": [
            "4 Dr Hatchback"
          ]
        },
        {
          "key": 25816,
          "value": "440i",
          "addon": [
            "2 Dr Convertible",
            "2 Dr Coupe"
          ]
        },
        {
          "key": 25818,
          "value": "440i Gran Coupe",
          "addon": [
            "4 Dr Hatchback"
          ]
        },
        {
          "key": 25817,
          "value": "440i xDrive",
          "addon": [
            "2 Dr Convertible",
            "2 Dr Coupe"
          ]
        },
        {
          "key": 25819,
          "value": "440i xDrive Gran Coupe",
          "addon": [
            "4 Dr Hatchback"
          ]
        },
        {
          "key": 187,
          "value": "530i",
          "addon": [
            "4 Dr Sedan"
          ]
        },
        {
          "key": 25850,
          "value": "530i xDrive",
          "addon": [
            "4 Dr Sedan"
          ]
        },
        {
          "key": 16148,
          "value": "535i GT",
          "addon": [
            "4 Dr Hatchback"
          ]
        },
        {
          "key": 16209,
          "value": "535i GT xDrive",
          "addon": [
            "4 Dr Hatchback"
          ]
        },
        {
          "key": 191,
          "value": "540i",
          "addon": [
            "4 Dr Sedan"
          ]
        },
        {
          "key": 25851,
          "value": "540i xDrive",
          "addon": [
            "4 Dr Sedan"
          ]
        },
        {
          "key": 16210,
          "value": "550i GT xDrive",
          "addon": [
            "4 Dr Hatchback"
          ]
        },
        {
          "key": 21518,
          "value": "640i",
          "addon": [
            "2 Dr Convertible",
            "2 Dr Coupe"
          ]
        },
        {
          "key": 21594,
          "value": "640i Gran Coupe",
          "addon": [
            "4 Dr Sedan"
          ]
        },
        {
          "key": 23445,
          "value": "640i xDrive",
          "addon": [
            "2 Dr Convertible",
            "2 Dr Coupe"
          ]
        },
        {
          "key": 23446,
          "value": "640i xDrive Gran Coupe",
          "addon": [
            "4 Dr Sedan"
          ]
        },
        {
          "key": 2827,
          "value": "650i",
          "addon": [
            "2 Dr Convertible",
            "2 Dr Coupe"
          ]
        },
        {
          "key": 22634,
          "value": "650i Gran Coupe",
          "addon": [
            "4 Dr Sedan"
          ]
        },
        {
          "key": 21519,
          "value": "650i xDrive",
          "addon": [
            "2 Dr Convertible",
            "2 Dr Coupe"
          ]
        },
        {
          "key": 23444,
          "value": "650i xDrive Gran Coupe",
          "addon": [
            "4 Dr Sedan"
          ]
        },
        {
          "key": 25856,
          "value": "740e xDrive",
          "addon": [
            "4 Dr Sedan"
          ]
        },
        {
          "key": 198,
          "value": "740i",
          "addon": [
            "4 Dr Sedan"
          ]
        },
        {
          "key": 25766,
          "value": "740i xDrive",
          "addon": [
            "4 Dr Sedan"
          ]
        },
        {
          "key": 27349,
          "value": "740Le xDrive",
          "addon": [
            "4 Dr Sedan"
          ]
        },
        {
          "key": 2795,
          "value": "750i",
          "addon": [
            "4 Dr Sedan"
          ]
        },
        {
          "key": 16132,
          "value": "750i xDrive",
          "addon": [
            "4 Dr Sedan"
          ]
        },
        {
          "key": 16133,
          "value": "750Li xDrive",
          "addon": [
            "4 Dr Sedan"
          ]
        },
        {
          "key": 24257,
          "value": "Alpina B6 xDrive Gran Coupe",
          "addon": [
            "4 Dr Sedan"
          ]
        },
        {
          "key": 6330,
          "value": "Alpina B7",
          "addon": [
            "4 Dr Sedan"
          ]
        },
        {
          "key": 23975,
          "value": "i3",
          "addon": [
            "4 Dr Hatchback"
          ]
        },
        {
          "key": 24258,
          "value": "i8",
          "addon": [
            "2 Dr Coupe"
          ]
        },
        {
          "key": 25750,
          "value": "M2",
          "addon": [
            "2 Dr Coupe"
          ]
        },
        {
          "key": 25809,
          "value": "M240i",
          "addon": [
            "2 Dr Convertible",
            "2 Dr Coupe"
          ]
        },
        {
          "key": 25810,
          "value": "M240i xDrive",
          "addon": [
            "2 Dr Convertible",
            "2 Dr Coupe"
          ]
        },
        {
          "key": 210,
          "value": "M3",
          "addon": [
            "4 Dr Sedan"
          ]
        },
        {
          "key": 23993,
          "value": "M4",
          "addon": [
            "2 Dr Convertible",
            "2 Dr Coupe"
          ]
        },
        {
          "key": 212,
          "value": "M6",
          "addon": [
            "2 Dr Convertible",
            "2 Dr Coupe"
          ]
        },
        {
          "key": 23443,
          "value": "M6 Gran Coupe",
          "addon": [
            "4 Dr Sedan"
          ]
        },
        {
          "key": 26419,
          "value": "M760i xDrive",
          "addon": [
            "4 Dr Sedan"
          ]
        },
        {
          "key": 26836,
          "value": "M760Li xDrive",
          "addon": [
            "4 Dr Sedan"
          ]
        },
        {
          "key": 21520,
          "value": "X1",
          "addon": [
            "4 Dr Sport Utility"
          ]
        },
        {
          "key": 2461,
          "value": "X3",
          "addon": [
            "4 Dr Sport Utility"
          ]
        },
        {
          "key": 24008,
          "value": "X4",
          "addon": [
            "4 Dr Sport Utility"
          ]
        },
        {
          "key": 213,
          "value": "X5",
          "addon": [
            "4 Dr Sport Utility"
          ]
        },
        {
          "key": 6803,
          "value": "X6",
          "addon": [
            "4 Dr Sport Utility"
          ]
        }
      ]
    },
    {
      "key": 2016,
      "value": "2016",
      "addon": [
        {
          "key": 1094,
          "value": "228i",
          "addon": [
            "2 Dr Convertible",
            "2 Dr Coupe"
          ]
        },
        {
          "key": 24006,
          "value": "228i xDrive",
          "addon": [
            "2 Dr Convertible",
            "2 Dr Coupe"
          ]
        },
        {
          "key": 165,
          "value": "320i",
          "addon": [
            "4 Dr Sedan"
          ]
        },
        {
          "key": 22944,
          "value": "320i xDrive",
          "addon": [
            "4 Dr Sedan"
          ]
        },
        {
          "key": 23524,
          "value": "328d",
          "addon": [
            "4 Dr Sedan"
          ]
        },
        {
          "key": 23525,
          "value": "328d xDrive",
          "addon": [
            "4 Dr Sedan",
            "4 Dr Wagon"
          ]
        },
        {
          "key": 178,
          "value": "328i",
          "addon": [
            "4 Dr Sedan"
          ]
        },
        {
          "key": 23491,
          "value": "328i GT xDrive",
          "addon": [
            "4 Dr Hatchback"
          ]
        },
        {
          "key": 6854,
          "value": "328i xDrive",
          "addon": [
            "4 Dr Sedan",
            "4 Dr Wagon"
          ]
        },
        {
          "key": 25756,
          "value": "330e",
          "addon": [
            "4 Dr Sedan"
          ]
        },
        {
          "key": 23492,
          "value": "335i GT xDrive",
          "addon": [
            "4 Dr Hatchback"
          ]
        },
        {
          "key": 25096,
          "value": "340i",
          "addon": [
            "4 Dr Sedan"
          ]
        },
        {
          "key": 25097,
          "value": "340i xDrive",
          "addon": [
            "4 Dr Sedan"
          ]
        },
        {
          "key": 23467,
          "value": "428i",
          "addon": [
            "2 Dr Convertible",
            "2 Dr Coupe"
          ]
        },
        {
          "key": 23994,
          "value": "428i Gran Coupe",
          "addon": [
            "4 Dr Hatchback"
          ]
        },
        {
          "key": 23469,
          "value": "428i xDrive",
          "addon": [
            "2 Dr Convertible",
            "2 Dr Coupe"
          ]
        },
        {
          "key": 23997,
          "value": "428i xDrive Gran Coupe",
          "addon": [
            "4 Dr Hatchback"
          ]
        },
        {
          "key": 23468,
          "value": "435i",
          "addon": [
            "2 Dr Convertible",
            "2 Dr Coupe"
          ]
        },
        {
          "key": 23995,
          "value": "435i Gran Coupe",
          "addon": [
            "4 Dr Hatchback"
          ]
        },
        {
          "key": 23470,
          "value": "435i xDrive",
          "addon": [
            "2 Dr Convertible",
            "2 Dr Coupe"
          ]
        },
        {
          "key": 23996,
          "value": "435i xDrive Gran Coupe",
          "addon": [
            "4 Dr Hatchback"
          ]
        },
        {
          "key": 186,
          "value": "528i",
          "addon": [
            "4 Dr Sedan"
          ]
        },
        {
          "key": 6841,
          "value": "528i xDrive",
          "addon": [
            "4 Dr Sedan"
          ]
        },
        {
          "key": 23526,
          "value": "535d",
          "addon": [
            "4 Dr Sedan"
          ]
        },
        {
          "key": 23527,
          "value": "535d xDrive",
          "addon": [
            "4 Dr Sedan"
          ]
        },
        {
          "key": 189,
          "value": "535i",
          "addon": [
            "4 Dr Sedan"
          ]
        },
        {
          "key": 16148,
          "value": "535i GT",
          "addon": [
            "4 Dr Hatchback"
          ]
        },
        {
          "key": 16209,
          "value": "535i GT xDrive",
          "addon": [
            "4 Dr Hatchback"
          ]
        },
        {
          "key": 6842,
          "value": "535i xDrive",
          "addon": [
            "4 Dr Sedan"
          ]
        },
        {
          "key": 2826,
          "value": "550i",
          "addon": [
            "4 Dr Sedan"
          ]
        },
        {
          "key": 16210,
          "value": "550i GT xDrive",
          "addon": [
            "4 Dr Hatchback"
          ]
        },
        {
          "key": 16207,
          "value": "550i xDrive",
          "addon": [
            "4 Dr Sedan"
          ]
        },
        {
          "key": 21518,
          "value": "640i",
          "addon": [
            "2 Dr Convertible",
            "2 Dr Coupe"
          ]
        },
        {
          "key": 21594,
          "value": "640i Gran Coupe",
          "addon": [
            "4 Dr Sedan"
          ]
        },
        {
          "key": 23445,
          "value": "640i xDrive",
          "addon": [
            "2 Dr Convertible",
            "2 Dr Coupe"
          ]
        },
        {
          "key": 23446,
          "value": "640i xDrive Gran Coupe",
          "addon": [
            "4 Dr Sedan"
          ]
        },
        {
          "key": 2827,
          "value": "650i",
          "addon": [
            "2 Dr Convertible",
            "2 Dr Coupe"
          ]
        },
        {
          "key": 22634,
          "value": "650i Gran Coupe",
          "addon": [
            "4 Dr Sedan"
          ]
        },
        {
          "key": 21519,
          "value": "650i xDrive",
          "addon": [
            "2 Dr Convertible",
            "2 Dr Coupe"
          ]
        },
        {
          "key": 23444,
          "value": "650i xDrive Gran Coupe",
          "addon": [
            "4 Dr Sedan"
          ]
        },
        {
          "key": 198,
          "value": "740i",
          "addon": [
            "4 Dr Sedan"
          ]
        },
        {
          "key": 2795,
          "value": "750i",
          "addon": [
            "4 Dr Sedan"
          ]
        },
        {
          "key": 16132,
          "value": "750i xDrive",
          "addon": [
            "4 Dr Sedan"
          ]
        },
        {
          "key": 22641,
          "value": "ActiveHybrid 5",
          "addon": [
            "4 Dr Sedan"
          ]
        },
        {
          "key": 25220,
          "value": "Alpina B6 Gran Coupe",
          "addon": [
            "4 Dr Sedan"
          ]
        },
        {
          "key": 24257,
          "value": "Alpina B6 xDrive Gran Coupe",
          "addon": [
            "4 Dr Sedan"
          ]
        },
        {
          "key": 23975,
          "value": "i3",
          "addon": [
            "4 Dr Hatchback"
          ]
        },
        {
          "key": 24258,
          "value": "i8",
          "addon": [
            "2 Dr Coupe"
          ]
        },
        {
          "key": 25750,
          "value": "M2",
          "addon": [
            "2 Dr Coupe"
          ]
        },
        {
          "key": 23967,
          "value": "M235i",
          "addon": [
            "2 Dr Convertible",
            "2 Dr Coupe"
          ]
        },
        {
          "key": 24007,
          "value": "M235i xDrive",
          "addon": [
            "2 Dr Convertible",
            "2 Dr Coupe"
          ]
        },
        {
          "key": 210,
          "value": "M3",
          "addon": [
            "4 Dr Sedan"
          ]
        },
        {
          "key": 23993,
          "value": "M4",
          "addon": [
            "2 Dr Convertible",
            "2 Dr Coupe"
          ]
        },
        {
          "key": 211,
          "value": "M5",
          "addon": [
            "4 Dr Sedan"
          ]
        },
        {
          "key": 212,
          "value": "M6",
          "addon": [
            "2 Dr Convertible",
            "2 Dr Coupe"
          ]
        },
        {
          "key": 23443,
          "value": "M6 Gran Coupe",
          "addon": [
            "4 Dr Sedan"
          ]
        },
        {
          "key": 21520,
          "value": "X1",
          "addon": [
            "4 Dr Sport Utility"
          ]
        },
        {
          "key": 2461,
          "value": "X3",
          "addon": [
            "4 Dr Sport Utility"
          ]
        },
        {
          "key": 24008,
          "value": "X4",
          "addon": [
            "4 Dr Sport Utility"
          ]
        },
        {
          "key": 213,
          "value": "X5",
          "addon": [
            "4 Dr Sport Utility"
          ]
        },
        {
          "key": 6803,
          "value": "X6",
          "addon": [
            "4 Dr Sport Utility"
          ]
        },
        {
          "key": 215,
          "value": "Z4",
          "addon": [
            "2 Dr Convertible"
          ]
        }
      ]
    },
    {
      "key": 2015,
      "value": "2015",
      "addon": [
        {
          "key": 1094,
          "value": "228i",
          "addon": [
            "2 Dr Convertible",
            "2 Dr Coupe"
          ]
        },
        {
          "key": 24006,
          "value": "228i xDrive",
          "addon": [
            "2 Dr Convertible",
            "2 Dr Coupe"
          ]
        },
        {
          "key": 165,
          "value": "320i",
          "addon": [
            "4 Dr Sedan"
          ]
        },
        {
          "key": 22944,
          "value": "320i xDrive",
          "addon": [
            "4 Dr Sedan"
          ]
        },
        {
          "key": 23524,
          "value": "328d",
          "addon": [
            "4 Dr Sedan"
          ]
        },
        {
          "key": 23525,
          "value": "328d xDrive",
          "addon": [
            "4 Dr Sedan",
            "4 Dr Wagon"
          ]
        },
        {
          "key": 178,
          "value": "328i",
          "addon": [
            "4 Dr Sedan"
          ]
        },
        {
          "key": 23491,
          "value": "328i GT xDrive",
          "addon": [
            "4 Dr Hatchback"
          ]
        },
        {
          "key": 6854,
          "value": "328i xDrive",
          "addon": [
            "4 Dr Sedan",
            "4 Dr Wagon"
          ]
        },
        {
          "key": 2883,
          "value": "335i",
          "addon": [
            "4 Dr Sedan"
          ]
        },
        {
          "key": 23492,
          "value": "335i GT xDrive",
          "addon": [
            "4 Dr Hatchback"
          ]
        },
        {
          "key": 6855,
          "value": "335i xDrive",
          "addon": [
            "4 Dr Sedan"
          ]
        },
        {
          "key": 23467,
          "value": "428i",
          "addon": [
            "2 Dr Convertible",
            "2 Dr Coupe"
          ]
        },
        {
          "key": 23994,
          "value": "428i Gran Coupe",
          "addon": [
            "4 Dr Hatchback"
          ]
        },
        {
          "key": 23469,
          "value": "428i xDrive",
          "addon": [
            "2 Dr Convertible",
            "2 Dr Coupe"
          ]
        },
        {
          "key": 23997,
          "value": "428i xDrive Gran Coupe",
          "addon": [
            "4 Dr Hatchback"
          ]
        },
        {
          "key": 23468,
          "value": "435i",
          "addon": [
            "2 Dr Convertible",
            "2 Dr Coupe"
          ]
        },
        {
          "key": 23995,
          "value": "435i Gran Coupe",
          "addon": [
            "4 Dr Hatchback"
          ]
        },
        {
          "key": 23470,
          "value": "435i xDrive",
          "addon": [
            "2 Dr Convertible",
            "2 Dr Coupe"
          ]
        },
        {
          "key": 23996,
          "value": "435i xDrive Gran Coupe",
          "addon": [
            "4 Dr Hatchback"
          ]
        },
        {
          "key": 186,
          "value": "528i",
          "addon": [
            "4 Dr Sedan"
          ]
        },
        {
          "key": 6841,
          "value": "528i xDrive",
          "addon": [
            "4 Dr Sedan"
          ]
        },
        {
          "key": 23526,
          "value": "535d",
          "addon": [
            "4 Dr Sedan"
          ]
        },
        {
          "key": 23527,
          "value": "535d xDrive",
          "addon": [
            "4 Dr Sedan"
          ]
        },
        {
          "key": 189,
          "value": "535i",
          "addon": [
            "4 Dr Sedan"
          ]
        },
        {
          "key": 16148,
          "value": "535i GT",
          "addon": [
            "4 Dr Hatchback"
          ]
        },
        {
          "key": 16209,
          "value": "535i GT xDrive",
          "addon": [
            "4 Dr Hatchback"
          ]
        },
        {
          "key": 6842,
          "value": "535i xDrive",
          "addon": [
            "4 Dr Sedan"
          ]
        },
        {
          "key": 2826,
          "value": "550i",
          "addon": [
            "4 Dr Sedan"
          ]
        },
        {
          "key": 16134,
          "value": "550i GT",
          "addon": [
            "4 Dr Hatchback"
          ]
        },
        {
          "key": 16210,
          "value": "550i GT xDrive",
          "addon": [
            "4 Dr Hatchback"
          ]
        },
        {
          "key": 16207,
          "value": "550i xDrive",
          "addon": [
            "4 Dr Sedan"
          ]
        },
        {
          "key": 21518,
          "value": "640i",
          "addon": [
            "2 Dr Convertible",
            "2 Dr Coupe"
          ]
        },
        {
          "key": 21594,
          "value": "640i Gran Coupe",
          "addon": [
            "4 Dr Sedan"
          ]
        },
        {
          "key": 23445,
          "value": "640i xDrive",
          "addon": [
            "2 Dr Convertible",
            "2 Dr Coupe"
          ]
        },
        {
          "key": 23446,
          "value": "640i xDrive Gran Coupe",
          "addon": [
            "4 Dr Sedan"
          ]
        },
        {
          "key": 2827,
          "value": "650i",
          "addon": [
            "2 Dr Convertible",
            "2 Dr Coupe"
          ]
        },
        {
          "key": 22634,
          "value": "650i Gran Coupe",
          "addon": [
            "4 Dr Sedan"
          ]
        },
        {
          "key": 21519,
          "value": "650i xDrive",
          "addon": [
            "2 Dr Convertible",
            "2 Dr Coupe"
          ]
        },
        {
          "key": 23444,
          "value": "650i xDrive Gran Coupe",
          "addon": [
            "4 Dr Sedan"
          ]
        },
        {
          "key": 198,
          "value": "740i",
          "addon": [
            "4 Dr Sedan"
          ]
        },
        {
          "key": 24269,
          "value": "740Ld xDrive",
          "addon": [
            "4 Dr Sedan"
          ]
        },
        {
          "key": 16151,
          "value": "740Li",
          "addon": [
            "4 Dr Sedan"
          ]
        },
        {
          "key": 22672,
          "value": "740Li xDrive",
          "addon": [
            "4 Dr Sedan"
          ]
        },
        {
          "key": 2795,
          "value": "750i",
          "addon": [
            "4 Dr Sedan"
          ]
        },
        {
          "key": 16132,
          "value": "750i xDrive",
          "addon": [
            "4 Dr Sedan"
          ]
        },
        {
          "key": 2794,
          "value": "750Li",
          "addon": [
            "4 Dr Sedan"
          ]
        },
        {
          "key": 16133,
          "value": "750Li xDrive",
          "addon": [
            "4 Dr Sedan"
          ]
        },
        {
          "key": 203,
          "value": "760Li",
          "addon": [
            "4 Dr Sedan"
          ]
        },
        {
          "key": 22670,
          "value": "ActiveHybrid 3",
          "addon": [
            "4 Dr Sedan"
          ]
        },
        {
          "key": 22641,
          "value": "ActiveHybrid 5",
          "addon": [
            "4 Dr Sedan"
          ]
        },
        {
          "key": 22671,
          "value": "ActiveHybrid 7",
          "addon": [
            "4 Dr Sedan"
          ]
        },
        {
          "key": 24257,
          "value": "Alpina B6 xDrive Gran Coupe",
          "addon": [
            "4 Dr Sedan"
          ]
        },
        {
          "key": 6330,
          "value": "Alpina B7",
          "addon": [
            "4 Dr Sedan"
          ]
        },
        {
          "key": 16155,
          "value": "Alpina B7 xDrive",
          "addon": [
            "4 Dr Sedan"
          ]
        },
        {
          "key": 16149,
          "value": "Alpina B7L",
          "addon": [
            "4 Dr Sedan"
          ]
        },
        {
          "key": 16156,
          "value": "Alpina B7L xDrive",
          "addon": [
            "4 Dr Sedan"
          ]
        },
        {
          "key": 23975,
          "value": "i3",
          "addon": [
            "4 Dr Hatchback"
          ]
        },
        {
          "key": 24258,
          "value": "i8",
          "addon": [
            "2 Dr Coupe"
          ]
        },
        {
          "key": 23967,
          "value": "M235i",
          "addon": [
            "2 Dr Convertible",
            "2 Dr Coupe"
          ]
        },
        {
          "key": 24007,
          "value": "M235i xDrive",
          "addon": [
            "2 Dr Coupe"
          ]
        },
        {
          "key": 210,
          "value": "M3",
          "addon": [
            "4 Dr Sedan"
          ]
        },
        {
          "key": 23993,
          "value": "M4",
          "addon": [
            "2 Dr Convertible",
            "2 Dr Coupe"
          ]
        },
        {
          "key": 211,
          "value": "M5",
          "addon": [
            "4 Dr Sedan"
          ]
        },
        {
          "key": 212,
          "value": "M6",
          "addon": [
            "2 Dr Convertible",
            "2 Dr Coupe"
          ]
        },
        {
          "key": 23443,
          "value": "M6 Gran Coupe",
          "addon": [
            "4 Dr Sedan"
          ]
        },
        {
          "key": 21520,
          "value": "X1",
          "addon": [
            "4 Dr Sport Utility"
          ]
        },
        {
          "key": 2461,
          "value": "X3",
          "addon": [
            "4 Dr Sport Utility"
          ]
        },
        {
          "key": 24008,
          "value": "X4",
          "addon": [
            "4 Dr Sport Utility"
          ]
        },
        {
          "key": 213,
          "value": "X5",
          "addon": [
            "4 Dr Sport Utility"
          ]
        },
        {
          "key": 6803,
          "value": "X6",
          "addon": [
            "4 Dr Sport Utility"
          ]
        },
        {
          "key": 215,
          "value": "Z4",
          "addon": [
            "2 Dr Convertible"
          ]
        }
      ]
    },
    {
      "key": 2014,
      "value": "2014",
      "addon": [
        {
          "key": 1094,
          "value": "228i",
          "addon": [
            "2 Dr Coupe"
          ]
        },
        {
          "key": 165,
          "value": "320i",
          "addon": [
            "4 Dr Sedan"
          ]
        },
        {
          "key": 22944,
          "value": "320i xDrive",
          "addon": [
            "4 Dr Sedan"
          ]
        },
        {
          "key": 23524,
          "value": "328d",
          "addon": [
            "4 Dr Sedan"
          ]
        },
        {
          "key": 23525,
          "value": "328d xDrive",
          "addon": [
            "4 Dr Sedan",
            "4 Dr Wagon"
          ]
        },
        {
          "key": 178,
          "value": "328i",
          "addon": [
            "4 Dr Sedan"
          ]
        },
        {
          "key": 23491,
          "value": "328i GT xDrive",
          "addon": [
            "4 Dr Hatchback"
          ]
        },
        {
          "key": 6854,
          "value": "328i xDrive",
          "addon": [
            "4 Dr Sedan",
            "4 Dr Wagon"
          ]
        },
        {
          "key": 2883,
          "value": "335i",
          "addon": [
            "4 Dr Sedan"
          ]
        },
        {
          "key": 23492,
          "value": "335i GT xDrive",
          "addon": [
            "4 Dr Hatchback"
          ]
        },
        {
          "key": 6855,
          "value": "335i xDrive",
          "addon": [
            "4 Dr Sedan"
          ]
        },
        {
          "key": 23467,
          "value": "428i",
          "addon": [
            "2 Dr Convertible",
            "2 Dr Coupe"
          ]
        },
        {
          "key": 23469,
          "value": "428i xDrive",
          "addon": [
            "2 Dr Convertible",
            "2 Dr Coupe"
          ]
        },
        {
          "key": 23468,
          "value": "435i",
          "addon": [
            "2 Dr Convertible",
            "2 Dr Coupe"
          ]
        },
        {
          "key": 23470,
          "value": "435i xDrive",
          "addon": [
            "2 Dr Coupe"
          ]
        },
        {
          "key": 186,
          "value": "528i",
          "addon": [
            "4 Dr Sedan"
          ]
        },
        {
          "key": 6841,
          "value": "528i xDrive",
          "addon": [
            "4 Dr Sedan"
          ]
        },
        {
          "key": 23526,
          "value": "535d",
          "addon": [
            "4 Dr Sedan"
          ]
        },
        {
          "key": 23527,
          "value": "535d xDrive",
          "addon": [
            "4 Dr Sedan"
          ]
        },
        {
          "key": 189,
          "value": "535i",
          "addon": [
            "4 Dr Sedan"
          ]
        },
        {
          "key": 16148,
          "value": "535i GT",
          "addon": [
            "4 Dr Hatchback"
          ]
        },
        {
          "key": 16209,
          "value": "535i GT xDrive",
          "addon": [
            "4 Dr Hatchback"
          ]
        },
        {
          "key": 6842,
          "value": "535i xDrive",
          "addon": [
            "4 Dr Sedan"
          ]
        },
        {
          "key": 2826,
          "value": "550i",
          "addon": [
            "4 Dr Sedan"
          ]
        },
        {
          "key": 16134,
          "value": "550i GT",
          "addon": [
            "4 Dr Hatchback"
          ]
        },
        {
          "key": 16210,
          "value": "550i GT xDrive",
          "addon": [
            "4 Dr Hatchback"
          ]
        },
        {
          "key": 16207,
          "value": "550i xDrive",
          "addon": [
            "4 Dr Sedan"
          ]
        },
        {
          "key": 21518,
          "value": "640i",
          "addon": [
            "2 Dr Convertible",
            "2 Dr Coupe"
          ]
        },
        {
          "key": 21594,
          "value": "640i Gran Coupe",
          "addon": [
            "4 Dr Sedan"
          ]
        },
        {
          "key": 23445,
          "value": "640i xDrive",
          "addon": [
            "2 Dr Convertible",
            "2 Dr Coupe"
          ]
        },
        {
          "key": 23446,
          "value": "640i xDrive Gran Coupe",
          "addon": [
            "4 Dr Sedan"
          ]
        },
        {
          "key": 2827,
          "value": "650i",
          "addon": [
            "2 Dr Convertible",
            "2 Dr Coupe"
          ]
        },
        {
          "key": 22634,
          "value": "650i Gran Coupe",
          "addon": [
            "4 Dr Sedan"
          ]
        },
        {
          "key": 21519,
          "value": "650i xDrive",
          "addon": [
            "2 Dr Convertible",
            "2 Dr Coupe"
          ]
        },
        {
          "key": 23444,
          "value": "650i xDrive Gran Coupe",
          "addon": [
            "4 Dr Sedan"
          ]
        },
        {
          "key": 198,
          "value": "740i",
          "addon": [
            "4 Dr Sedan"
          ]
        },
        {
          "key": 16151,
          "value": "740Li",
          "addon": [
            "4 Dr Sedan"
          ]
        },
        {
          "key": 22672,
          "value": "740Li xDrive",
          "addon": [
            "4 Dr Sedan"
          ]
        },
        {
          "key": 2795,
          "value": "750i",
          "addon": [
            "4 Dr Sedan"
          ]
        },
        {
          "key": 16132,
          "value": "750i xDrive",
          "addon": [
            "4 Dr Sedan"
          ]
        },
        {
          "key": 2794,
          "value": "750Li",
          "addon": [
            "4 Dr Sedan"
          ]
        },
        {
          "key": 16133,
          "value": "750Li xDrive",
          "addon": [
            "4 Dr Sedan"
          ]
        },
        {
          "key": 203,
          "value": "760Li",
          "addon": [
            "4 Dr Sedan"
          ]
        },
        {
          "key": 22670,
          "value": "ActiveHybrid 3",
          "addon": [
            "4 Dr Sedan"
          ]
        },
        {
          "key": 22641,
          "value": "ActiveHybrid 5",
          "addon": [
            "4 Dr Sedan"
          ]
        },
        {
          "key": 22671,
          "value": "ActiveHybrid 7",
          "addon": [
            "4 Dr Sedan"
          ]
        },
        {
          "key": 6330,
          "value": "Alpina B7",
          "addon": [
            "4 Dr Sedan"
          ]
        },
        {
          "key": 16155,
          "value": "Alpina B7 xDrive",
          "addon": [
            "4 Dr Sedan"
          ]
        },
        {
          "key": 16149,
          "value": "Alpina B7L",
          "addon": [
            "4 Dr Sedan"
          ]
        },
        {
          "key": 16156,
          "value": "Alpina B7L xDrive",
          "addon": [
            "4 Dr Sedan"
          ]
        },
        {
          "key": 23975,
          "value": "i3",
          "addon": [
            "4 Dr Hatchback"
          ]
        },
        {
          "key": 24258,
          "value": "i8",
          "addon": [
            "2 Dr Coupe"
          ]
        },
        {
          "key": 23967,
          "value": "M235i",
          "addon": [
            "2 Dr Coupe"
          ]
        },
        {
          "key": 211,
          "value": "M5",
          "addon": [
            "4 Dr Sedan"
          ]
        },
        {
          "key": 212,
          "value": "M6",
          "addon": [
            "2 Dr Convertible",
            "2 Dr Coupe"
          ]
        },
        {
          "key": 23443,
          "value": "M6 Gran Coupe",
          "addon": [
            "4 Dr Sedan"
          ]
        },
        {
          "key": 21520,
          "value": "X1",
          "addon": [
            "4 Dr Sport Utility"
          ]
        },
        {
          "key": 2461,
          "value": "X3",
          "addon": [
            "4 Dr Sport Utility"
          ]
        },
        {
          "key": 213,
          "value": "X5",
          "addon": [
            "4 Dr Sport Utility"
          ]
        },
        {
          "key": 6803,
          "value": "X6",
          "addon": [
            "4 Dr Sport Utility"
          ]
        },
        {
          "key": 215,
          "value": "Z4",
          "addon": [
            "2 Dr Convertible"
          ]
        }
      ]
    }
  ]
}